Metadata-Version: 1.0
Name: gaus-bin-probability
Version: 0.2
Summary: Gaussian and Binomial distributions
Home-page: UNKNOWN
Author: Patrick Walukagga
Author-email: pwalukagga@gmail.com
License: UNKNOWN
Platform: UNKNOWN
